iqradre/__init__.py
iqradre/classify/__init__.py
iqradre/classify/datamodule.py
iqradre/classify/module.py
iqradre/classify/predictor.py
iqradre/classify/utils.py
iqradre/detect/__init__ copy.py
iqradre/detect/__init__.py
iqradre/detect/datasets/__init__.py
iqradre/detect/datasets/custom.py
iqradre/detect/datasets/loader.py
iqradre/detect/datasets/synthtext.py
iqradre/detect/datasets/utils.py
iqradre/detect/models/__init__.py
iqradre/detect/models/backbone.py
iqradre/detect/models/craft.py
iqradre/detect/models/refinenet.py
iqradre/detect/models/utils.py
iqradre/detect/models/vgg16_bn.py
iqradre/detect/nn/__init__.py
iqradre/detect/nn/functional.py
iqradre/detect/nn/loss.py
iqradre/detect/ops/__init__.py
iqradre/detect/ops/affinity.py
iqradre/detect/ops/box_ops.py
iqradre/detect/ops/boxes.py
iqradre/detect/ops/gaussian.py
iqradre/detect/ops/synthtext.py
iqradre/detect/ops/transform.py
iqradre/detect/pred/__init__.py
iqradre/detect/pred/functional.py
iqradre/detect/pred/net.py
iqradre/detect/pred/prediction.py
iqradre/detect/trainer/__init__.py
iqradre/detect/trainer/helper.py
iqradre/detect/trainer/task.py
iqradre/detect/transforms/__init__.py
iqradre/detect/transforms/functional.py
iqradre/detect/transforms/transforms.py
iqradre/detect/utils/__init__.py
iqradre/detect/utils/craft_utils.py
iqradre/detect/utils/file_utils.py
iqradre/detect/utils/imgproc.py
iqradre/detect/utils/viz.py
iqradre/detect/utils/viz_utils.py
iqradre/extract/__init__.py
iqradre/extract/config/__init__.py
iqradre/extract/config/label.py
iqradre/extract/config/token.py
iqradre/extract/data/__init__.py
iqradre/extract/data/dataset.py
iqradre/extract/data/loader.py
iqradre/extract/data/utils.py
iqradre/extract/ops/__init__.py
iqradre/extract/ops/boxes_ops.py
iqradre/extract/prod/__init__.py
iqradre/extract/prod/prod.py
iqradre/extract/prod/utils.py
iqradre/extract/trainer/__init__.py
iqradre/extract/trainer/metrics.py
iqradre/extract/trainer/task.py
iqradre/prod/__init__.py
iqradre-0.2.1.dist-info/METADATA
iqradre-0.2.1.dist-info/WHEEL
iqradre-0.2.1.dist-info/top_level.txt
iqradre-0.2.1.dist-info/RECORD
