Metadata-Version: 2.1
Name: iqradre
Version: 0.2.1
Summary: UNKNOWN
Home-page: https://github.com/nunenuh/iqradre
Author: Lalu Erfandi Maula Yusnu
Author-email: nunenuh@gmail.com
License: UNKNOWN
Project-URL: Bug Reports, https://github.com/nunenuh/iqradre/issues
Project-URL: Source, https://github.com/nunenuh/iqradre/
Keywords: pytorch deep learning machine learning
Platform: UNKNOWN
Classifier: Development Status :: 3 - Alpha
Classifier: Intended Audience :: Developers
Classifier: Topic :: Software Development
Classifier: Programming Language :: Python :: 3.8
Requires-Python: >=3.8
Requires-Dist: absl-py (==0.13.0)
Requires-Dist: aiohttp (==3.7.4.post0)
Requires-Dist: alembic (==1.4.1)
Requires-Dist: astunparse (==1.6.3)
Requires-Dist: async-timeout (==3.0.1)
Requires-Dist: cachetools (==4.2.2)
Requires-Dist: clang (==5.0)
Requires-Dist: databricks-cli (==0.15.0)
Requires-Dist: deskew (==0.10.33)
Requires-Dist: docker (==5.0.2)
Requires-Dist: fire (==0.4.0)
Requires-Dist: flatbuffers (==1.12)
Requires-Dist: fsspec (==2021.8.1)
Requires-Dist: gast (==0.4.0)
Requires-Dist: gitdb (==4.0.7)
Requires-Dist: gitpython (==3.1.18)
Requires-Dist: google-auth (==1.35.0)
Requires-Dist: google-auth-oauthlib (==0.4.6)
Requires-Dist: google-pasta (==0.2.0)
Requires-Dist: grpcio (==1.40.0)
Requires-Dist: gunicorn (==20.1.0)
Requires-Dist: h5py (==3.1.0)
Requires-Dist: imutils (==0.5.4)
Requires-Dist: keras (==2.6.0)
Requires-Dist: keras-preprocessing (==1.1.2)
Requires-Dist: mako (==1.1.5)
Requires-Dist: markdown (==3.3.4)
Requires-Dist: mlflow (==1.20.0)
Requires-Dist: multidict (==5.1.0)
Requires-Dist: numpy (==1.19.5)
Requires-Dist: oauthlib (==3.1.1)
Requires-Dist: opencv-python (==4.4.0.46)
Requires-Dist: opencv-python-headless (==4.5.1.48)
Requires-Dist: opt-einsum (==3.3.0)
Requires-Dist: prometheus-flask-exporter (==0.18.2)
Requires-Dist: protobuf (==3.17.3)
Requires-Dist: pyasn1 (==0.4.8)
Requires-Dist: pyasn1-modules (==0.2.8)
Requires-Dist: pydeprecate (==0.3.1)
Requires-Dist: pytesseract (==0.3.8)
Requires-Dist: python-editor (==1.0.4)
Requires-Dist: pytorch-lightning (==1.4.5)
Requires-Dist: querystring-parser (==1.2.4)
Requires-Dist: requests-oauthlib (==1.3.0)
Requires-Dist: rsa (==4.7.2)
Requires-Dist: sacremoses (==0.0.45)
Requires-Dist: seqeval (==1.2.2)
Requires-Dist: shapely (==1.7.1)
Requires-Dist: smmap (==4.0.0)
Requires-Dist: sqlparse (==0.4.2)
Requires-Dist: tabulate (==0.8.9)
Requires-Dist: tensorboard (==2.6.0)
Requires-Dist: tensorboard-data-server (==0.6.1)
Requires-Dist: tensorboard-plugin-wit (==1.8.0)
Requires-Dist: tensorboardx (==2.0)
Requires-Dist: tensorflow (==2.6.0)
Requires-Dist: tensorflow-estimator (==2.6.0)
Requires-Dist: tensorflow-gpu (==2.6.0)
Requires-Dist: termcolor (==1.1.0)
Requires-Dist: tokenizers (==0.9.4)
Requires-Dist: torchmetrics (==0.5.1)
Requires-Dist: transformers (==4.1.1)
Requires-Dist: websocket-client (==1.2.1)
Requires-Dist: yarl (==1.6.3)
Provides-Extra: dev
Requires-Dist: check-manifest ; extra == 'dev'
Provides-Extra: test
Requires-Dist: coverage ; extra == 'test'
